{"1":{"nome":"","email":"abobora@gmail.com","senha":"$2y$10$6KyR2zebR19mFHohqT6xauDb6G3kVmiUCm\/ZOsVXSjIq4QAjgiU0a"},"2":{"nome":"","email":"jpcm86@gmail.com","senha":"$2y$10$vwQwgAotQp7pIrLJJH6Yqutrr\/Atfqi9t\/WrTmisaMlxyZ9B\/gb7e"},"3":{"nome":"aaa","email":"aaa@aaa.com","senha":"$2y$10$MKV0Ku2gX2ZqXrkkkG7SJuAUBGpX1k4UswppcZKyp2lxLdK.SRV7m"},"4":{"nome":"","email":"","senha":"$2y$10$K5Mnh1W1aWy9c0SOHE98tOpTc2AEPHR1CxndnwAbwORjfIQM9nBdO"},"5":{"nome":"Caio","email":"caio@email.com","senha":"$2y$10$PISviWFEDjzXrpyLjWdtzuWFli1Bawn.82UzcREAqiC.lrBoOu.iC"}}